{
  "ep_length_mean": {
    "steps": [
      500
    ],
    "timestamps": [
      "2024-11-21T01:46:59.845369"
    ],
    "values": [
      500.0
    ]
  },
  "epsilon": {
    "steps": [
      500
    ],
    "timestamps": [
      "2024-11-21T01:46:59.845395"
    ],
    "values": [
      1.0
    ]
  },
  "return_mean": {
    "steps": [
      500
    ],
    "timestamps": [
      "2024-11-21T01:46:59.820287"
    ],
    "values": [
      0.0
    ]
  },
  "return_std": {
    "steps": [
      500
    ],
    "timestamps": [
      "2024-11-21T01:46:59.842628"
    ],
    "values": [
      0.0
    ]
  }
}